discord_oauth2_api/__init__.py
discord_oauth2_api/get_user_data.py
Discord_oauth2_API-0.1.4.dist-info/LICENSE
Discord_oauth2_API-0.1.4.dist-info/METADATA
Discord_oauth2_API-0.1.4.dist-info/WHEEL
Discord_oauth2_API-0.1.4.dist-info/top_level.txt
Discord_oauth2_API-0.1.4.dist-info/RECORD
