Metadata-Version: 2.1
Name: Discord-oauth2-API
Version: 0.1.4
Summary: Discord oauth2 api basic client
Home-page: https://github.com/Vlakboss/Discord-oauth2-API
Author: Matej Ruzicka
Author-email: vlakboss@vlakoznaltech.eu
Classifier: Programming Language :: Python :: 3
Classifier: License :: OSI Approved :: MIT License
Classifier: Operating System :: OS Independent
Requires-Python: >=3.8
License-File: LICENSE
